list_dataloaders/__init__.py
list_dataloaders/list_dataloaders_wrapper.py
list_dataloaders-1.0.1.dist-info/METADATA
list_dataloaders-1.0.1.dist-info/WHEEL
list_dataloaders-1.0.1.dist-info/top_level.txt
list_dataloaders-1.0.1.dist-info/RECORD
