Metadata-Version: 2.1
Name: list-dataloaders
Version: 1.0.1
Summary: This package contains a pure-python class that wraps a list of dataloaders and allows to iterate over them in a random order.
Home-page: https://github.com/MorenoLaQuatra/list-dataloaders
Author: Moreno La Quatra
Author-email: moreno.laquatra@gmail.com
Classifier: Programming Language :: Python :: 3.9
Classifier: Programming Language :: Python :: 3.8
Classifier: Programming Language :: Python :: 3.7
Classifier: Operating System :: OS Independent
Classifier: License :: OSI Approved :: GNU General Public License v3 (GPLv3)
Classifier: Programming Language :: Python :: 3
Requires-Dist: torch (>=1.7)
Provides-Extra: dev
Requires-Dist: pytest (>=3.7) ; extra == 'dev'
